ChengzhenZaibutongChangheXiyinNvrendeYaoshi/README.md
ChengzhenZaibutongChangheXiyinNvrendeYaoshi/__init__.py
ChengzhenZaibutongChangheXiyinNvrendeYaoshi/__main__.py
ChengzhenZaibutongChangheXiyinNvrendeYaoshi/file.epub
ChengzhenZaibutongChangheXiyinNvrendeYaoshi/index.html
ChengzhenZaibutongChangheXiyinNvrendeYaoshi/css/__init__.py
ChengzhenZaibutongChangheXiyinNvrendeYaoshi/css/annotations.css
ChengzhenZaibutongChangheXiyinNvrendeYaoshi/css/main.css
ChengzhenZaibutongChangheXiyinNvrendeYaoshi/css/normalize.css
ChengzhenZaibutongChangheXiyinNvrendeYaoshi/css/popup.css
ChengzhenZaibutongChangheXiyinNvrendeYaoshi/font/__init__.py
ChengzhenZaibutongChangheXiyinNvrendeYaoshi/font/fontello.eot
ChengzhenZaibutongChangheXiyinNvrendeYaoshi/font/fontello.svg
ChengzhenZaibutongChangheXiyinNvrendeYaoshi/font/fontello.ttf
ChengzhenZaibutongChangheXiyinNvrendeYaoshi/font/fontello.woff
ChengzhenZaibutongChangheXiyinNvrendeYaoshi/img/__init__.py
ChengzhenZaibutongChangheXiyinNvrendeYaoshi/img/annotator-glyph-sprite.png
ChengzhenZaibutongChangheXiyinNvrendeYaoshi/img/annotator-icon-sprite.png
ChengzhenZaibutongChangheXiyinNvrendeYaoshi/img/apple-touch-icon.png
ChengzhenZaibutongChangheXiyinNvrendeYaoshi/img/cancelfullscreen.png
ChengzhenZaibutongChangheXiyinNvrendeYaoshi/img/close.png
ChengzhenZaibutongChangheXiyinNvrendeYaoshi/img/fullscreen.png
ChengzhenZaibutongChangheXiyinNvrendeYaoshi/img/loader.gif
ChengzhenZaibutongChangheXiyinNvrendeYaoshi/img/menu-icon.png
ChengzhenZaibutongChangheXiyinNvrendeYaoshi/img/save.png
ChengzhenZaibutongChangheXiyinNvrendeYaoshi/img/saved.png
ChengzhenZaibutongChangheXiyinNvrendeYaoshi/img/settings-s.png
ChengzhenZaibutongChangheXiyinNvrendeYaoshi/img/settings.png
ChengzhenZaibutongChangheXiyinNvrendeYaoshi/img/star.png
ChengzhenZaibutongChangheXiyinNvrendeYaoshi/js/__init__.py
ChengzhenZaibutongChangheXiyinNvrendeYaoshi/js/epub.js
ChengzhenZaibutongChangheXiyinNvrendeYaoshi/js/epub.min.js
chengzhen_zaibutong_changhe_xiyin_nvrende_yaoshi-2022.10.11.0.dist-info/METADATA
chengzhen_zaibutong_changhe_xiyin_nvrende_yaoshi-2022.10.11.0.dist-info/WHEEL
chengzhen_zaibutong_changhe_xiyin_nvrende_yaoshi-2022.10.11.0.dist-info/entry_points.txt
chengzhen_zaibutong_changhe_xiyin_nvrende_yaoshi-2022.10.11.0.dist-info/top_level.txt
chengzhen_zaibutong_changhe_xiyin_nvrende_yaoshi-2022.10.11.0.dist-info/RECORD
